rofilde_demo/__init__.py
rofilde_demo/hello.py
rofilde_demo-0.1.5.dist-info/WHEEL
rofilde_demo-0.1.5.dist-info/METADATA
rofilde_demo-0.1.5.dist-info/RECORD
