Metadata-Version: 2.1
Name: rofilde-demo
Version: 0.1.5
Summary: README.rst
Author: Rofilde Hasudungan
Author-email: rofilde@gmail.com
Requires-Python: >=3.8,<4.0
Classifier: Programming Language :: Python :: 3
Classifier: Programming Language :: Python :: 3.10
Classifier: Programming Language :: Python :: 3.8
Classifier: Programming Language :: Python :: 3.9
Requires-Dist: readme
